dspg/__init__.py
dspg/cli.py
dspg/sandbox.py
dspg-0.1.0.dist-info/entry_points.txt
dspg-0.1.0.dist-info/WHEEL
dspg-0.1.0.dist-info/METADATA
dspg-0.1.0.dist-info/RECORD
